{
  "accentColor": "{{appsmith.theme.colors.primaryColor}}",
  "animateLoading": true,
  "borderRadius": "{{appsmith.theme.borderRadius.appBorderRadius}}",
  "bottomRow": 4,
  "boxShadow": "none",
  "defaultOptionValue": "",
  "dynamicBindingPathList": [
    {
      "key": "accentColor"
    },
    {
      "key": "borderRadius"
    },
    {
      "key": "sourceData"
    }
  ],
  "dynamicHeight": "FIXED",
  "dynamicPropertyPathList": [
    {
      "key": "sourceData"
    }
  ],
  "dynamicTriggerPathList": [
    {
      "key": "onOptionChange"
    }
  ],
  "isDisabled": false,
  "isFilterable": true,
  "isLoading": false,
  "isRequired": true,
  "isVisible": true,
  "key": "nqzujm8468",
  "labelAlignment": "left",
  "labelPosition": "Left",
  "labelText": "Corr. Bank",
  "labelTextSize": "0.875rem",
  "labelTooltip": "",
  "labelWidth": "8",
  "leftColumn": 20,
  "maxDynamicHeight": 9000,
  "minDynamicHeight": 4,
  "minWidth": 450,
  "mobileBottomRow": 6,
  "mobileLeftColumn": 0,
  "mobileRightColumn": 20,
  "mobileTopRow": 0,
  "needsErrorInfo": false,
  "onOptionChange": "",
  "optionLabel": "bank_identity",
  "optionValue": "id",
  "parentColumnSpace": 10.94140625,
  "parentId": "qhhwf58xbx",
  "parentRowSpace": 10,
  "placeholderText": "Select option",
  "renderMode": "CANVAS",
  "responsiveBehavior": "fill",
  "rightColumn": 64,
  "serverSideFiltering": false,
  "sourceData": "{{getBankIdentitiesQuery.data}}",
  "topRow": 0,
  "type": "SELECT_WIDGET",
  "version": 1,
  "widgetId": "uskxaw9qk9",
  "widgetName": "CCAF_Bank_Corr_Select"
}